kakao_zipcode/__init__.py
django_kakao_zipcode-0.1.1.dist-info/LICENSE
django_kakao_zipcode-0.1.1.dist-info/METADATA
django_kakao_zipcode-0.1.1.dist-info/WHEEL
django_kakao_zipcode-0.1.1.dist-info/top_level.txt
django_kakao_zipcode-0.1.1.dist-info/zip-safe
django_kakao_zipcode-0.1.1.dist-info/RECORD
